Metadata-Version: 1.0
Name: biostrand-admin
Version: 0.1
Summary: admin
Home-page: https://github.com/BioStrand/biostrand-admin
Author: UNKNOWN
Author-email: UNKNOWN
License: UNKNOWN
Platform: UNKNOWN
